README.md
setup.cfg
setup.py
conjuno/__init__.py
conjuno/_version.py
conjuno/cell.py
conjuno/console.py
conjuno/format.py
conjuno/help.py
conjuno/keymaps.py
conjuno/log.py
conjuno/main.py
conjuno/notebook.py
conjuno.egg-info/PKG-INFO
conjuno.egg-info/SOURCES.txt
conjuno.egg-info/dependency_links.txt
conjuno.egg-info/entry_points.txt
conjuno.egg-info/requires.txt
conjuno.egg-info/top_level.txt