Metadata-Version: 2.1
Name: conjuno
Version: 0.2.1
Summary: Console Jupyter Notebook
Home-page: https://conjuno.com
Author: Michael Tatton
Classifier: License :: OSI Approved :: MIT License
Classifier: Operating System :: OS Independent
Classifier: Programming Language :: Python :: 3
Requires-Python: >=3.9
Provides-Extra: test
